<class>
<keyword> function </keyword>
<keyword> void </keyword>
<identifier> start </identifier>
<symbol> ( </symbol>
<symbol> ) </symbol>
<symbol> { </symbol>
<varDec>
<keyword> var </keyword>
<keyword> int </keyword>
<identifier> i </identifier>
<symbol> ; </symbol>
</varDec>
<keyword> let </keyword>
<identifier> i </identifier>
<symbol> = </symbol>
<intConstant> 10 </intConstant>
<symbol> ; </symbol>
<keyword> do </keyword>
<identifier> Output </identifier>
<symbol> . </symbol>
<identifier> printInt </identifier>
<symbol> ( </symbol>
<identifier> i </identifier>
<symbol> ) </symbol>
<symbol> ; </symbol>
<keyword> return </keyword>
<symbol> ; </symbol>
<symbol> } </symbol>
</class>
